mcp_pokemon_server_csdemo/__init__.py
mcp_pokemon_server_csdemo/zekang.py
mcp_pokemon_server_csdemo-1.1.0.dist-info/METADATA
mcp_pokemon_server_csdemo-1.1.0.dist-info/WHEEL
mcp_pokemon_server_csdemo-1.1.0.dist-info/entry_points.txt
mcp_pokemon_server_csdemo-1.1.0.dist-info/RECORD
