Metadata-Version: 2.4
Name: mcp-pokemon-server-csdemo
Version: 1.1.0
Summary: Add your description here
Requires-Python: >=3.10
Requires-Dist: mcp[cli]>=1.7.1
